mdplus/__init__.py
mdplus/_version.py
mdplus/fast.cpython-312-darwin.so
mdplus/multiscale.py
mdplus/pca.py
mdplus/refinement.py
mdplus/refinement_dev.py
mdplus/refinement_master.py
mdplus/utils.py
mdplus-0.1.1.data/scripts/glimps-backmap
mdplus-0.1.1.data/scripts/glimps-map
mdplus-0.1.1.data/scripts/glimps-train
mdplus-0.1.1.dist-info/LICENSE.txt
mdplus-0.1.1.dist-info/METADATA
mdplus-0.1.1.dist-info/WHEEL
mdplus-0.1.1.dist-info/top_level.txt
mdplus-0.1.1.dist-info/RECORD
