Metadata-Version: 2.2
Name: mdplus
Version: 0.1.1
Summary: Tools for molecular dynamics simulation setup and analysis.
Home-page: https://bitbucket.org/claughton/mdplus/overview
Download-URL: https://bitbucket.org/claughton/mdplus/get/0.1.1.tar.gz
Author: The University of Nottingham & BSC
Author-email: charles.laughton@nottingham.ac.uk
License: BSD license.
Classifier: Development Status :: 4 - Beta
Classifier: Intended Audience :: Science/Research
Classifier: Environment :: Console
Classifier: License :: OSI Approved :: BSD License
Classifier: Programming Language :: Python
Classifier: Programming Language :: Python :: 3
Classifier: Programming Language :: Python :: 3.4
Classifier: Programming Language :: Python :: 3.5
Classifier: Programming Language :: Python :: 3.6
Classifier: Programming Language :: Python :: 3.7
Classifier: Topic :: Scientific/Engineering
Classifier: Operating System :: MacOS :: MacOS X
Classifier: Operating System :: POSIX
Classifier: Operating System :: Unix
License-File: LICENSE.txt
Requires-Dist: networkx
Requires-Dist: scipy
Requires-Dist: scikit-learn
Dynamic: author
Dynamic: author-email
Dynamic: classifier
Dynamic: description
Dynamic: description-content-type
Dynamic: download-url
Dynamic: home-page
Dynamic: license
Dynamic: requires-dist
Dynamic: summary
